django_vectorstore_indexed_model/__init__.py
django_vectorstore_indexed_model/admin.py
django_vectorstore_indexed_model/apps.py
django_vectorstore_indexed_model/models.py
django_vectorstore_indexed_model/schemas.py
django_vectorstore_indexed_model/settings.py
django_vectorstore_indexed_model/tests.py
django_vectorstore_indexed_model/version.py
django_vectorstore_indexed_model/views.py
django_vectorstore_indexed_model/migrations/__init__.py
django_vectorstore_indexed_model-0.2.0.dist-info/licenses/LICENSE
django_vectorstore_indexed_model-0.2.0.dist-info/METADATA
django_vectorstore_indexed_model-0.2.0.dist-info/WHEEL
django_vectorstore_indexed_model-0.2.0.dist-info/top_level.txt
django_vectorstore_indexed_model-0.2.0.dist-info/RECORD
